README.rst
setup.py
cloudarmy/__init__.py
cloudarmy.egg-info/PKG-INFO
cloudarmy.egg-info/SOURCES.txt
cloudarmy.egg-info/dependency_links.txt
cloudarmy.egg-info/entry_points.txt
cloudarmy.egg-info/requires.txt
cloudarmy.egg-info/top_level.txt
cloudarmy/cli/__init__.py
cloudarmy/cli/__main__.py
cloudarmy/contrib/__init__.py
cloudarmy/contrib/conditions/__init__.py
cloudarmy/contrib/conditions/environment.py
cloudarmy/contrib/mixins/__init__.py
cloudarmy/contrib/mixins/environment.py
cloudarmy/contrib/parameters/__init__.py
cloudarmy/contrib/parameters/environment.py
cloudarmy/core/__init__.py
cloudarmy/core/base.py