Metadata-Version: 1.1
Name: cloudarmy
Version: 0.1
Summary: Cloudformation templating engine
Home-page: https://github.com/geeknam/cloudarmy
Author: Nam Ngo
Author-email: namngology@gmail.com
License: Apache License 2.0
Keywords: aws,cloudformation,cloud,stack,workflow
Platform: UNKNOWN
Classifier: Development Status :: 5 - Production/Stable
Classifier: Environment :: Console
Classifier: Intended Audience :: Developers
Classifier: License :: OSI Approved :: Apache Software License
Classifier: Programming Language :: Python :: 2
Classifier: Programming Language :: Python :: 2.7
Classifier: Programming Language :: Python :: 3
Classifier: Programming Language :: Python :: 3.4
